pint/__init__.py
pint/bayesian.py
pint/binaryconvert.py
pint/config.py
pint/derived_quantities.py
pint/erfautils.py
pint/event_toas.py
pint/eventstats.py
pint/exceptions.py
pint/fermi_toas.py
pint/fits_utils.py
pint/fitter.py
pint/gridutils.py
pint/logging.py
pint/mcmc_fitter.py
pint/modelutils.py
pint/phase.py
pint/pint_matrix.py
pint/plot_utils.py
pint/polycos.py
pint/pulsar_ecliptic.py
pint/pulsar_mjd.py
pint/random_models.py
pint/residuals.py
pint/sampler.py
pint/simulation.py
pint/solar_system_ephemerides.py
pint/toa.py
pint/toa_select.py
pint/types.py
pint/utils.py
pint/data/examples/B1855+09_NANOGrav_9yv1.gls.par
pint/data/examples/B1855+09_NANOGrav_9yv1.tim
pint/data/examples/B1855+09_NANOGrav_dfg+12.tim
pint/data/examples/B1855+09_NANOGrav_dfg+12_TAI.par
pint/data/examples/J0030+0451_P8_15.0deg_239557517_458611204_ft1weights_GEO_wt.gt.0.4.fits
pint/data/examples/J0613-sim.par
pint/data/examples/J0613-sim.tim
pint/data/examples/J0740+6620.FCP+21.wb.DMX3.0.par
pint/data/examples/J0740+6620.FCP+21.wb.tim
pint/data/examples/J1028-5819-example.par
pint/data/examples/J1028-5819-example.tim
pint/data/examples/J1614-2230_NANOGrav_12yv3.wb.gls.par
pint/data/examples/J1614-2230_NANOGrav_12yv3.wb.tim
pint/data/examples/NGC6440E.par
pint/data/examples/NGC6440E.par.good
pint/data/examples/NGC6440E.tim
pint/data/examples/PSRJ0030+0451_psrcat.par
pint/data/examples/README.md
pint/data/examples/templateJ0030.3gauss
pint/data/examples/test-wb-0.par
pint/data/examples/test-wb-0.tim
pint/data/examples/waves.par
pint/data/examples/waves_withpn.tim
pint/data/runtime/README.md
pint/data/runtime/ecliptic.dat
pint/data/runtime/observatories.json
pint/extern/__init__.py
pint/extern/_version.py
pint/models/__init__.py
pint/models/absolute_phase.py
pint/models/astrometry.py
pint/models/binary_bt.py
pint/models/binary_dd.py
pint/models/binary_ddk.py
pint/models/binary_ell1.py
pint/models/chromatic_model.py
pint/models/cmwavex.py
pint/models/dispersion_model.py
pint/models/dmwavex.py
pint_pulsar-1.1.4.dist-info/AUTHORS.rst
pint_pulsar-1.1.4.dist-info/LICENSE.md
pint_pulsar-1.1.4.dist-info/METADATA
pint_pulsar-1.1.4.dist-info/WHEEL
pint_pulsar-1.1.4.dist-info/entry_points.txt
pint_pulsar-1.1.4.dist-info/top_level.txt
pint_pulsar-1.1.4.dist-info/RECORD
