Metadata-Version: 2.1
Name: pint-pulsar
Version: 1.1.4
Summary: A Pulsar Timing Package, written in Python from scratch
Author: Scott Ransom, Paul Demorest, Paul Ray, et al.
Author-email: Luo Jing <sransom@nrao.edu>
License: License :: OSI Approved :: BSD License
Project-URL: Homepage, https://github.com/nanograv/PINT
Project-URL: Documentation, https://nanograv-pint.readthedocs.io/
Classifier: Intended Audience :: Science/Research
Classifier: License :: OSI Approved :: BSD License
Classifier: Operating System :: OS Independent
Classifier: Programming Language :: Python
Classifier: Programming Language :: Python :: 3
Classifier: Programming Language :: Python :: 3.9
Classifier: Programming Language :: Python :: 3.10
Classifier: Programming Language :: Python :: 3.11
Classifier: Programming Language :: Python :: 3.12
Classifier: Programming Language :: Python :: 3.13
Classifier: Topic :: Scientific/Engineering :: Astronomy
Classifier: Topic :: Software Development :: Libraries :: Python Modules
Requires-Python: >=3.9
License-File: LICENSE.md
License-File: AUTHORS.rst
Requires-Dist: numpy >=1.23.0
Requires-Dist: astropy >=5.0.5
Requires-Dist: pyerfa
Requires-Dist: scipy >=1.9.0
Requires-Dist: jplephem >=2.6
Requires-Dist: matplotlib >=3.4.3
Requires-Dist: emcee >=3.0.1
Requires-Dist: corner >=2.0.1
Requires-Dist: uncertainties
Requires-Dist: loguru
Requires-Dist: nestle >=0.2.0
Requires-Dist: numdifftools
